wpilib_mcp/__init__.py
wpilib_mcp/plugin_loader.py
wpilib_mcp/server.py
wpilib_mcp/tool_router.py
wpilib_mcp/plugins/__init__.py
wpilib_mcp/plugins/base.py
wpilib_mcp/plugins/ctre/__init__.py
wpilib_mcp/plugins/ctre/build_index.py
wpilib_mcp/plugins/ctre/plugin.py
wpilib_mcp/plugins/ctre/data/index.json
wpilib_mcp/plugins/photonvision/__init__.py
wpilib_mcp/plugins/photonvision/build_index.py
wpilib_mcp/plugins/photonvision/plugin.py
wpilib_mcp/plugins/photonvision/data/index.json
wpilib_mcp/plugins/redux/__init__.py
wpilib_mcp/plugins/redux/build_index.py
wpilib_mcp/plugins/redux/plugin.py
wpilib_mcp/plugins/redux/data/index.json
wpilib_mcp/plugins/rev/__init__.py
wpilib_mcp/plugins/rev/build_index.py
wpilib_mcp/plugins/rev/plugin.py
wpilib_mcp/plugins/rev/data/index.json
wpilib_mcp/plugins/wpilib/__init__.py
wpilib_mcp/plugins/wpilib/build_index.py
wpilib_mcp/plugins/wpilib/plugin.py
wpilib_mcp/plugins/wpilib/data/index_2025.json
wpilib_mcp/plugins/wpilib/data/index_stable.json
wpilib_mcp/utils/__init__.py
wpilib_mcp/utils/fetch.py
wpilib_mcp/utils/html.py
wpilib_mcp/utils/indexer.py
wpilib_mcp/utils/search.py
first_agentic_csa-0.3.12.dist-info/METADATA
first_agentic_csa-0.3.12.dist-info/WHEEL
first_agentic_csa-0.3.12.dist-info/entry_points.txt
first_agentic_csa-0.3.12.dist-info/licenses/LICENSE
first_agentic_csa-0.3.12.dist-info/RECORD
