Metadata-Version: 2.4
Name: first-agentic-csa
Version: 0.3.12
Summary: Plugin-based FRC documentation agent as an MCP server for WPILib and vendor libraries
Author: Rami Mouro
License: BSD-3-Clause
License-File: LICENSE
Keywords: csa,documentation,first,frc,mcp,robotics,wpilib
Classifier: Development Status :: 3 - Alpha
Classifier: Intended Audience :: Developers
Classifier: License :: OSI Approved :: BSD License
Classifier: Programming Language :: Python :: 3.11
Classifier: Programming Language :: Python :: 3.12
Requires-Python: >=3.11
Requires-Dist: beautifulsoup4>=4.12.0
Requires-Dist: httpx>=0.27.0
Requires-Dist: lxml>=5.0.0
Requires-Dist: mcp>=1.0.0
Requires-Dist: rank-bm25>=0.2.2
Provides-Extra: dev
Requires-Dist: pytest-asyncio>=0.23.0; extra == 'dev'
Requires-Dist: pytest>=8.0.0; extra == 'dev'
